{
  "updatedAt": "2026-06-10T17:45:29.655Z",
  "data": {
    "LMT": {
      "name": "록히드마틴",
      "px": 529.78,
      "dayChange": 0,
      "periodChange": 3.42,
      "prices": [
        512.25,
        521,
        519.94,
        520.41,
        516.01,
        528.31,
        526.63,
        522.59,
        522.79,
        533.24,
        532.9,
        531.14,
        537.21,
        530.45,
        516.5,
        513.43,
        512.03,
        519.05,
        523.76,
        520.07,
        530.13,
        529.78
      ],
      "currency": "USD",
      "state": "CLOSED",
      "market": "US",
      "fundamentals": {
        "high52w": 692,
        "low52w": 410.11,
        "volume": 441035
      }
    },
    "RTX": {
      "name": "RTX",
      "px": 179.07,
      "dayChange": 0,
      "periodChange": 0.26,
      "prices": [
        178.61,
        178.89,
        178.11,
        175.68,
        171.18,
        175.95,
        174.49,
        174.85,
        175.98,
        177.01,
        178.97,
        176.59,
        178.96,
        179.66,
        174.41,
        174.26,
        172.55,
        179.41,
        180.99,
        178.66,
        181.56,
        179.07
      ],
      "currency": "USD",
      "state": "CLOSED",
      "market": "US",
      "fundamentals": {
        "high52w": 214.5,
        "low52w": 135.43,
        "volume": 2499558
      }
    },
    "047810": {
      "name": "한국항공우주",
      "px": 137600,
      "dayChange": 0,
      "periodChange": -24.66,
      "prices": [
        169500,
        165900,
        163500,
        172200,
        161100,
        161700,
        161800,
        158000,
        164500,
        168400,
        169900,
        165700,
        167900,
        168300,
        163000,
        147000,
        141500,
        139000,
        125000,
        127700
      ],
      "currency": "KRW",
      "state": "CLOSED",
      "market": "KR",
      "fundamentals": {
        "marketCap": "13조 4,126억",
        "per": "67.82배",
        "pbr": "7.20배",
        "cnsPer": "38.83배",
        "divYield": "0.36%",
        "foreignRatio": "26.87%",
        "high52w": "215,500",
        "low52w": "83,000"
      }
    },
    "012450": {
      "name": "한화에어로스페이스",
      "px": 1031000,
      "dayChange": 0,
      "periodChange": -22.74,
      "prices": [
        1315000,
        1284000,
        1286000,
        1306000,
        1216000,
        1227000,
        1286000,
        1249000,
        1248000,
        1261000,
        1251000,
        1244000,
        1200000,
        1173000,
        1138000,
        1070000,
        1068000,
        1049000,
        1006000,
        1016000
      ],
      "currency": "KRW",
      "state": "CLOSED",
      "market": "KR",
      "fundamentals": {
        "marketCap": "53조 1,619억",
        "per": "32.38배",
        "pbr": "5.33배",
        "cnsPer": "24.77배",
        "divYield": "0.68%",
        "foreignRatio": "45.31%",
        "high52w": "1,713,000",
        "low52w": "760,000"
      }
    }
  },
  "benchmark": {
    "theme": [
      0,
      -0.65,
      -1.13,
      0.22,
      -3.98,
      -2.41,
      -1.56,
      -2.97,
      -1.86,
      -0.39,
      -0.1,
      -1.27,
      -1.16,
      -1.84,
      -4.7,
      -8.53,
      -9.68,
      -9.11,
      -11.54,
      -11.46
    ],
    "kospi": [
      0,
      -2.29,
      0.28,
      2.03,
      -4.21,
      -3.91,
      -7.04,
      -7.84,
      -0.09,
      0.33,
      2.88,
      5.2,
      4.64,
      8.36,
      12.35,
      12.52,
      10.45,
      4.33,
      -4.32,
      3.51
    ],
    "sp500": [
      0,
      0.77,
      -0.48,
      -0.55,
      -1.22,
      -0.15,
      0.02,
      0.39,
      1.01,
      1.02,
      1.6,
      1.82,
      2.09,
      2.22,
      1.47,
      1.88,
      -0.81,
      -0.52,
      -0.77,
      -2
    ]
  }
}