{
  "updatedAt": "2026-07-23T18:48:21.894Z",
  "count": 21,
  "stats": {
    "today": 13,
    "yesterday": 7,
    "weekAvg": 3,
    "sources": 8,
    "heat": "hot"
  },
  "items": [
    {
      "s": "조선일보",
      "t": "“인천바이오과학기술원 만들고 ‘AI 허브’로 도시 경쟁력 높일 것”",
      "d": "",
      "u": "https://www.chosun.com/national/regional/2026/07/24/EUSW6D36XRHXND2JKTHQNHQF5A/",
      "m": "07. 23. PM 03:43",
      "ts": 1784821380000,
      "fullText": "",
      "impact": "positive",
      "takeaway": "인천 바이오·AI 허브 조성으로 투자 여건 개선"
    },
    {
      "s": "조선일보",
      "t": "삼성바이오로직스 2분기 매출 1.3조",
      "d": "",
      "u": "https://www.chosun.com/economy/science/2026/07/24/RZGGQBJ33JCTZHCCPXONU5IP2Q/",
      "m": "07. 23. PM 03:34",
      "ts": 1784820840000,
      "fullText": "",
      "impact": "positive",
      "takeaway": "삼성바이오로직스 매출 1.3조 달성, 업계 성장 기대"
    },
    {
      "s": "동아일보",
      "t": "삼성바이오, 6분기째 영업익 40%대… ‘공장 풀가동’ 효과",
      "d": "삼성바이오로직스가 6개 분기 연속 영업이익률 40%대를 유지했다.  삼성바이오로직스는 23일 2분기(4∼6월) 매출 1조3209억 원, 영업이익 5864억 원을 기록했다고 공시했다. 지난해 같은 기간보다 매출은 30%, 영업이익은 23% 증가한 수치다. 영업이익률은 44.4%로 2025년 1분기부터 6개 분기째 40%대를 지켰다. 상반기(1∼6월)로 따져도 매출 2조5780억 원, 영업이익은 1조1672억 원으로 전년 동기보다 각각 28%, 29% 증가했다.  인천 송도 1∼4공장의 안정적인 가동과 환율 효과가 실적을 뒷받침했다는 평가가 나온다. 회사는 송도 5공장과 4월 인수한 미국 록빌 생산시설의 가동이 본격화하고 환율이 뒷받침되면 올해 매출 성장률 전망치(15∼20%)의 상단, 즉 20% 달성이 가능할",
      "u": "https://www.donga.com/news/Economy/article/all/20260723/134353740/2",
      "m": "07. 23. PM 03:30",
      "ts": 1784820600000,
      "fullText": "김재형 기자 구독",
      "impact": "positive",
      "takeaway": "공장 풀가동으로 영업이익 40%대 유지, 수익성 강화"
    },
    {
      "s": "Bloomberg Tech",
      "t": "Thermo Fisher Rises as Instrument Demand Recovery Lifts Outlook",
      "d": "Thermo Fisher Scientific Inc. raised its revenue forecast after stronger-than-expected spending by biotech and pharma customers and a rebound in laboratory instrument demand helped pushed second-quarter sales past expectations. Shares jumped.",
      "u": "https://www.bloomberg.com/news/articles/2026-07-23/thermo-fisher-rises-as-instrument-demand-recovery-lifts-outlook",
      "m": "07. 23. PM 03:13",
      "ts": 1784819601000,
      "fullText": "",
      "impact": "neutral",
      "takeaway": "테마와 직접 무관"
    },
    {
      "s": "한국경제",
      "t": "동아쏘시오, 동아제약 흡수합병",
      "d": "",
      "u": "https://www.hankyung.com/article/2026072328781",
      "m": "07. 23. AM 10:41",
      "ts": 1784803295000,
      "fullText": "코리아마켓 한경 PREMIUM9 AI를 넘어서는 성공투자 구독하기 AI 추천 뉴스 AI 추천 뉴스 팝업 닫기 동아쏘시오, 동아제약 흡수합병 입력 2026.07.23 19:41 수정 2026.07.24 00:30 지면 A25 기사 스크랩 기사 스크랩 댓글 댓글 기사 공유 공유 글자크기 조절 글자크기 프린트 프린트 이지현 기자 구독하기 구글 검색 선호 출처로 추가 Google 검색에서 한국경제 기사를 더 자주 볼 수 있습니다. 10월 사업 지주회사로 출범 &quot;중복상장 우려 해소 차원&quot; 동아쏘시오홀딩스 가 일반의약품 사업 자회사인 동아제약을 흡수합병하고 사업 지주회사 체제로 전환한다. 중복상장 우려를 없애고 지주회사 주주가치를 제고하기 위해서다. 동아쏘시오홀딩스는 23일 장 마감 후 100% 자회사인 동아제약을 흡수합병하기로 했다고 공시했다. 합병 기일은 오는 10월 1일이다. 신주 발행 없는 소규모 합병 방식으로, 합병 후에도 동아쏘시오홀딩스 주주 구성과 지분율은 바뀌지 않는다. 회사는 합병 후 정관 변경 등을 통해 사명을 소멸회사인 동아제약으로 바꿀 것으로 알려졌다. 동아쏘시오홀딩스는 2013년 동아쏘시오그룹이 지주사 체제로 전환하면서 출범했다. &lsquo;박카스&rsquo; 등 일반의약품 사업 전담 자회사인 동아제약은 헬스케어 제품과 더마 화장품 등을 출시하면서 그룹 내 현금 창출원 역할을 했다. 지난해 동아제약 매출은 7263억원, 영업이익은 869억원이다. 이번 흡수합병으로 지주사인 동아쏘시오홀딩스는 일반의약품 사업을 내재화해 신규 투자, 자회사 관리 등을 강화할 수 있는 현금 창출 역량을 확보하게 됐다. 동아쏘시오홀딩스는 합병 목적과 관련해 &ldquo;핵심 자회사인 동아제약의 컨슈머 헬스케어 시장 경쟁력과 안정적인 현금 흐름 창출 능력을 확보하면 사업형 지주회사로 신성장 동력에 투자하는 재원을 마련할 수 있을 것&rdquo;이라고 밝혔다. 이어 &ldquo;지배구조를 단순화하고 신속한 의사결정으로 경영 효율성을 제고할 계획&rdquo;이라며 &ldquo;자회사 중복상장 우려에 따른 지주회사 할인 요소를 해소해 기업가치를 제고하기 위한 목적도 있다&rdquo;고 설명했다. 유가증권시장 상장사인 동아쏘시오홀딩스는 이날 정규장에서 4.55% 상승한 8만500원에 거래를 마쳤다. 이지현 기자 bluesky@hankyung.com 좋아요 싫어요 후속기사 원해요 ⓒ 한경닷컴, 무단전재 및 재배포 금지 한국경제 구독신청 한경 프리미엄9 구독신청 이지현 기자 ADVERTISEMENT 관련 뉴스 1 영업이익 흑자 전환…OCI홀딩스 '상한가' OCI홀딩스가 올해 2분기 흑자 전환 기대에 상한가를 기록했다. 이날 발표한 2분기 영업이익이1080억원으로 흑자 전환에 성공하면서 투자심리를 자극한 것으로 풀이된다.23일 유가증권시장에서 OCI홀딩스는 가격제한폭(... 2026.07.23 17:51 2 약국 플랫폼·IR…'이색업종' IPO 눈길 인공지능(AI)과 로봇 등 첨단 기술주가 주도하는 기업공개(IPO) 시장에 이색 업종의 기업들이 잇달아 도전장을 내밀고 있다.23일 투자은행(IB)업계에 따르면 아이알큐더스(투자자 소통·홍보), 동승(부... 2026.07.23 17:50 3 신동빈 회장, 현금 확보 위해 롯데쇼핑 지분 423억어치 매각 신동빈 롯데그룹 회장이 현금 유동성 확보를 위해 보유 중인 롯데쇼핑 주식 32만4100주(1.15%)를 매각한다고 22일 공시했다. 매도가는 주당 13만400원으로 총 422억6264만원 규모다. 거래예정일은 다음달... 2026.07.22 18:12 ADVERTISEMENT 많이 본 뉴스 1 \"자식도 싫다는 회사\"…땅 팔고 폐업 택하자 정부 칼 빼들었다 2026.07.22 17:53 2 품절, 품절, 품절…\"이게 1000원?\" 다이소 또 터졌다 2026.07.21 20:00 3 제주까지 몰려온 어선 1000척…바다 뒤덮은 中 '비밀 병력' 2026.07.22 18:02 4 핫스톡 \"손절할 뻔\"…주가 50% 빠졌는데 삼성 한마디에 '반전' 2026.07.23 06:30 5 \"",
      "impact": "positive",
      "takeaway": "동아쏘시오·동아제약 흡수합병으로 시너지 기대"
    },
    {
      "s": "전자신문",
      "t": "'국가대표 보건의료기술' 30선 선정 추진…바이오헬스 초격차 노린다",
      "d": "정부가 국가대표 보건의료 기술 30선을 선정하고 연구개발부터 사업화까지 전주기 지원하는 사업에 나선다. 보건복지부는 23일 서울 중구 롯데호텔에서 2026년 제2차 보건의료기술정책심의위원회(보기심)를 열고 보건의료 국가대표기술 30선 선정 계획, 보건의료 연구데이터 공동 관리규정 제정안 등을 논의했다. 이날 행사는 공동위원장인 조명찬 민간위원장과 보건복지부 이형훈 제2차관을 비롯해 과학기술정보통신부, 산업통상부, 식품의약품안전처, 질병관리청 등",
      "u": "https://www.etnews.com/20260723000455",
      "m": "07. 23. AM 09:37",
      "ts": 1784799442000,
      "fullText": "과학 바이오 '국가대표 보건의료기술' 30선 선정 추진…바이오헬스 초격차 노린다 발행일 : 2026-07-23 18:37 공유하기 페이스북 X(트위터) 메일 URL 복사 글자크기 설정 가 작게 가 보통 가 크게 정부가 국가대표 보건의료 기술 30선을 선정하고 연구개발부터 사업화까지 전주기 지원하는 사업에 나선다. 보건복지부는 23일 서울 중구 롯데호텔에서 2026년 제2차 보건의료기술정책심의위원회(보기심)를 열고 보건의료 국가대표기술 30선 선정 계획, 보건의료 연구데이터 공동 관리규정 제정안 등을 논의했다. 이형훈 보건복지부 제2차관이 23일 서울 중구 롯데호텔에서 열린 2026년 제2차 보건의료기술정책심의위원회(보기심)에서 발언하고 있다. (사진=보건복지부) 이날 행사는 공동위원장인 조명찬 민간위원장과 보건복지부 이형훈 제2차관을 비롯해 과학기술정보통신부, 산업통상부, 식품의약품안전처, 질병관리청 등 정부 기관과 국립암센터, 한국보건산업진흥원 등 공공기관, 민간 전문가 등 18명이 참석했다. 이날 보기심에서는 △보건의료 국가대표기술 30선 선정 추진계획(안) △보건의료 연구개발사업 연구데이터 공동 관리 규정 제정(안) △2027년 보건복지부 주요 연구개발 투자 방향 등을 논의했다. 우선 국가적 보건의료 난제 해결에 크게 기여하면서 글로벌 시장 선도와 산업경쟁력 확보가 가능한 전략기술 30선을 선정하기로 했다. 시장 창출, 기술 초격차, 현장 현안, 난제 극복의 네 가지 핵심 분야로 구분해 다음 달 중 선정한다. 선정된 기술은 연구개발부터 사업화까지 전주기로 지원할 계획이다. '보건의료 연구개발사업 연구데이터 공동 관리규정'을 복지부와 질병청이 함께 제정하는 방안도 추진한다. 보건의료 연구 데이터는 설문, 검진 등의 수집 정보, 신체 계측, 혈액 검사 정보, 엑스레이 등 의료영상 데이터, 병리 슬라이스 이미지, 웨어러블 기기와 환경센서 수집 정보, 전장유전체 정보 등을 포함한다. 복지부와 질병청이 지원하는 국가연구개발사업의 연구 데이터는 질병관리청의 보건의료연구자원정보센터(CODA)에 등록·기탁하도록 할 방침이다. 기존 CODA 데이터 등록·기탁은 연구자가 자율적으로 참여해왔다. 향후 공동 관리규정이 제정되면 양 기관이 운영·관리하는 보건의료기술 연구개발 사업 대상으로 연구개발과제 수행 과정에서 생산·관리되는 보건의료 연구 데이터에 대해 적용한다. 정부는 공동 관리규정을 제정하면 등록·기탁 대상이 확대되고 폭넓은 연구 데이터를 확보하게 돼 다양한 연구과제에 활용도가 높아질 것으로 기대했다. 연구자료 활용 시 데이터를 비식별화하고 필요한 최소한의 접근권한을 부여해 개인정보 보호와 정보보안 사고 예방을 꾀한다. 내년도 보건의료 연구개발은 바이오헬스 5대 강국 실현을 목표로 △바이오헬스 패러다임 전환 △데이터 기반의 AI 의료 △지역·필수 의료 강화 △임무 중심의 도전적 연구에 대한 연구개발 과제를 기획하고 투자를 강화할 계획이다. 이형훈 보건복지부 제2차관은 “보건의료 국가연구개발사업은 국민 건강과 바이오헬스산업 경쟁력을 동시에 뒷받침하는 핵심 기반으로 자리잡고 있다”며 “국가대표기술을 전략적으로 육성하고 연구 데이터 활용 기반을 체계적으로 구축해 글로벌 바이오헬스 강국 실현에 박차를 가하겠다”고 말했다. 배옥진 기자 withok@etnews.com",
      "impact": "positive",
      "takeaway": "보건의료 30선 선정 추진으로 바이오헬스 경쟁력 강화"
    },
    {
      "s": "전자신문",
      "t": "'韓 ICT 50년 역사 망라' ETRI, 온라인 50년사' 공개",
      "d": "한국전자통신연구원(ETRI)이 창립 50주년을 맞아, 지난 반세기 대한민국 정보통신기술(ICT) 산업 발전을 이끈 연구개발(R&D) 역사와 주요 성과를 집대성한 'ETRI 온라인 50년사'를 구축·공개했다고 23일 밝혔다. 온라인 50년사는 국민 누구나 시간·공간 제약 없이 대한민국 ICT 발전 역사를 이해·활용할 수 있도록 구축한 디지털 역사 아카이브다. 대한민국 ICT 성장 과정과 국가 R&D 발자취를 디지털 콘텐츠로 구현했다. 특히 지난해",
      "u": "https://www.etnews.com/20260723000450",
      "m": "07. 23. AM 09:10",
      "ts": 1784797855000,
      "fullText": "과학 과학 '韓 ICT 50년 역사 망라' ETRI, 온라인 50년사' 공개 발행일 : 2026-07-23 18:10 공유하기 페이스북 X(트위터) 메일 URL 복사 글자크기 설정 가 작게 가 보통 가 크게 ETRI는 연구개발(R&D) 역사와 주요 성과를 집대성한 'ETRI 온라인 50년사'를 구축, 공개했다. 한국전자통신연구원(ETRI)이 창립 50주년을 맞아, 지난 반세기 대한민국 정보통신기술(ICT) 산업 발전을 이끈 연구개발(R&D) 역사와 주요 성과를 집대성한 'ETRI 온라인 50년사'를 구축·공개했다고 23일 밝혔다. 온라인 50년사는 국민 누구나 시간·공간 제약 없이 대한민국 ICT 발전 역사를 이해·활용할 수 있도록 구축한 디지털 역사 아카이브다. 대한민국 ICT 성장 과정과 국가 R&D 발자취를 디지털 콘텐츠로 구현했다. 특히 지난해 개관한 ETRI 역사관을 온라인에서도 실제 전시관을 방문한 것처럼 생생하게 둘러볼 수 있도록 했다. 또 다양한 연구성과와 역사 콘텐츠를 유기적으로 연결해 국민과 미래 세대가 ICT 교육의 장으로 활용할 수 있는 지식 플랫폼으로 구성했다. 신 콘텐츠를 지속적으로 추가·확장할 수 있는 온라인 플랫폼으로 구현해, 살아있는 역사 기록체계 역할도 수행하게 된다. 먼저 '반세기 연혁 (History of ETRI)'에서는 1976년 연구원 설립부터 현재까지의 주요 사건과 연구성과를 연도별로 정리했다. 전전자교환기(TDX) 개발을 비롯해 메모리반도체(DRAM), 세계 최초 디지털이동통신시스템(CDMA) 상용화, 디지털멀티미디어방송(DMB), 휴대인터넷(WiBro), LTE-Advanced, 인공지능(AI), 6G, 양자기술 등 대한민국 ICT 발전을 이끈 대표 기술을 시대별 흐름에 따라 쉽게 이해할 수 있도록 구성했다. '50대 대표성과'에서는 대한민국 ICT 발전에 결정적인 역할을 수행한 대표 연구성과를 분야별로 소개한다. 50대 대표성과를 포함해 ETRI가 지난 50년간 개발한 기술 산업 파급효과는 약 494조 원 규모인 것으로 분석됐다. 50년간 연평균 9.9조 원의 경제적 가치를 창출한 셈이다. 온라인 50년사에서 대표 기술별 산업적 가치와 경제적 효과를 인포그래픽과 다양한 시각자료를 통해 쉽게 확인할 수 있다. 'ETRI 50년, 길을 만들어온 사람들'에서는 지난 50년 ETRI를 이끌어온 연구자들의 인터뷰 영상을 통해 연구 현장의 도전과 열정 그리고 대한민국 ICT 혁신을 이끌어온 이야기를 전한다. '사진·뉴스 아카이브'에서는 ETRI의 지난 50년을 사진과 신문기사를 통해 만나볼 수 있다. '디지털 역사관'에서는 ETRI 역사관 내부를 360도 파노라마 영상으로 구현해 실제 역사관을 방문한 것처럼 자유롭게 관람할 수 있도록 했다. 박세웅 원장은 “ETRI의 지난 50년은 대한민국 ICT 발전의 역사 그 자체”라며 “온라인 50년사가 과거의 혁신을 기록하는 데 머무르지 않고 미래 세대가 새로운 도전을 이어갈 수 있는 살아있는 지식 플랫폼이자 대한민국 ICT 혁신의 나침반이 되기를 기대한다”고 말했다. 김영준 기자 kyj85@etnews.com",
      "impact": "neutral",
      "takeaway": "테마와 직접 무관"
    },
    {
      "s": "전자신문",
      "t": "성신여대 재학생,  2026년 하계 한국항체학회 정기학술대회 우수포스터상 수상",
      "d": "성신여자대학교는 이세영 바이오신약의과학부 학생이 최근 열린 '2026년 하계 한국항체학회 정기학술대회'에서 우수포스터상을 수상했다고 23일 밝혔다. 성신여대 이세영 학생은 'Discovery of PD-L1-specific nanobody for immune checkpoint blockade'를 주제로 연구 성과를 발표해 주목을 받았다. 이번 연구는 암세포가 면역세포의 공격을 회피하는 데 활용하는 단백질 PD-1/PD-L1 상호작용을 차단해",
      "u": "https://www.etnews.com/20260723000444",
      "m": "07. 23. AM 08:57",
      "ts": 1784797056000,
      "fullText": "정치·정책 교육 성신여대 재학생, 2026년 하계 한국항체학회 정기학술대회 우수포스터상 수상 발행일 : 2026-07-23 17:57 공유하기 페이스북 X(트위터) 메일 URL 복사 글자크기 설정 가 작게 가 보통 가 크게 이세영 바이오신약의과학부 학생(사진=성신여대) 성신여자대학교는 이세영 바이오신약의과학부 학생이 최근 열린 '2026년 하계 한국항체학회 정기학술대회'에서 우수포스터상을 수상했다고 23일 밝혔다. 성신여대 이세영 학생은 'Discovery of PD-L1-specific nanobody for immune checkpoint blockade'를 주제로 연구 성과를 발표해 주목을 받았다. 이번 연구는 암세포가 면역세포의 공격을 회피하는 데 활용하는 단백질 PD-1/PD-L1 상호작용을 차단해 면역 회피를 억제하는 새로운 나노바디(nanobody)를 개발하는데 초점을 맞췄다. 최근 개발되는 항체의약품 분야에서는 PD-L1, CTLA-4 등과 같은 면역관문 단백질에 결합해 암세포의 면역 회피 기전을 차단하는 이중항체(Bispecific Antibody) 형태의 치료제 개발이 활발히 이뤄지고 있다. 나노바디는 일반 항체보다 크기가 작고 안정성이 높아 이중항체 치료제 개발에 적합한 차세대 약물 모달리티로 주목받고 있는 만큼, 이번 연구성과 역시 차세대 면역항암제 개발의 중요한 밑거름이 될 것으로 기대된다. 이세영 학생은 “연구를 지도해 주신 교수님과 동료 연구원들에게 감사드린다”며 “항체공학 연구에 매진하며 끊임없이 학문적으로 성장해 나가겠다”고 수상 소감을 전했다. 조호현 기자 hohyun@etnews.com 에듀플러스",
      "impact": "positive",
      "takeaway": "항체학회 포스터상 수상으로 바이오·제약 연구 역량 부각"
    },
    {
      "s": "한경 IT",
      "t": "동아쏘시오홀딩스, 동아제약 흡수합병…사업지주사 체제 전환",
      "d": "",
      "u": "https://www.hankyung.com/article/202607232687i",
      "m": "07. 23. AM 08:57",
      "ts": 1784797051000,
      "fullText": "BIO Insight 한경 PREMIUM9 AI를 넘어서는 성공투자 구독하기 AI 추천 뉴스 AI 추천 뉴스 팝업 닫기 동아쏘시오홀딩스, 동아제약 흡수합병…사업지주사 체제 전환 입력 2026.07.23 17:57 수정 2026.07.23 17:57 기사 스크랩 기사 스크랩 댓글 댓글 기사 공유 공유 글자크기 조절 글자크기 프린트 프린트 이지현 기자 구독하기 구글 검색 선호 출처로 추가 Google 검색에서 한국경제 기사를 더 자주 볼 수 있습니다. 동아쏘시오홀딩스 사옥 전경 동아쏘시오홀딩스 가 일반의약품 사업 사회사인 동아제약을 흡수 합병해 &#39;사업지주회사&#39; 체제로 전환한다. 주요 자회사 중복상장 우려를 없애고 지주사의 자금 유동성 등을 강화할 수 있을 것으로 내다봤다. 동아쏘시오홀딩스는 23일 오전 이사회를 열고 100% 자회사인 동아제약을 흡수합병하기로 결정했다고 밝혔다. 합병기일은 오는 10월 1일이다. 신주 발행이 없는 소규모 합병 방식으로, 합병 후에도 동아쏘시오홀딩스 주주구성과 지분율은 바뀌지 않는다. 추후 정관변경 등을 통해 동아제약의 사명도 유지할 것으로 알려졌다. 동아쏘시오홀딩스는 2013년 동아쏘시오그룹이 지주사로 전환하면서 출범했다. 박카스 등 일반의약품 사업 전담 자회사인 동아제약은 헬스케어 제품, 더마 화장품 등을 출시하면서 동아쏘시오그룹 내 든든한 &#39;캐시카우&#39; 역할을 했다. 이번 흡수 합병으로 지주사인 동아쏘시오홀딩스는 컨슈머 헬스케어 사업을 내재화해 안정적인 현금창출 역량을 확보하게 됐다. 이와 함께 그룹 신규 투자, 신성장동력 확보, 자회사 관리 등을 병행하는 사업지주회사 체제로 전환된다. 동아쏘시오홀딩스와 동아제약이 단일 거버넌스 체제를 구축해 책임 경영을 강화할 수 있을 것으로 업체 측은 내다봤다. 주요 자회사 중복 상장 우려도 사라졌다. 통합법인을 통해 이커머스 채널을 다각화하고 글로벌 리테일 체인에 진입하는 등 해외 시장 진출을 확대할 계획이다. 동아쏘시오홀딩스 관계자는 &quot;이번 합병은 2013년 추진했던 지주사 전환 성과를 계승하면서 글로벌 헬스케어 시장을 선도하는 기업으로 도약하기 위한 결단&quot;며 &quot;통합된 자원과 자본을 바탕으로 신성장동력 확보를 위한 투자를 늘려 기업가치와 주주가치를 극대화할 것&quot;이라고 했다. 동아쏘시오홀딩스는 합병기일 전에 임시주주총회를 열고 합병에 따른 정관변경, 이사 선임 등의 안건을 상정할 예정이다. 이지현 기자 bluesky@hankyung.com 좋아요 싫어요 후속기사 원해요 ⓒ 한경닷컴, 무단전재 및 재배포 금지 한국경제 구독신청 한경 프리미엄9 구독신청 이지현 기자 ADVERTISEMENT 관련 뉴스 1 동아제약, 간편하게 뿌리는 무좀치료제 ‘터비뉴 더블액션 에어로솔’ 출시 동아제약은 간편하게 뿌리는 스프레이 타입 무좀치료제 터비뉴 더블액션 에어로솔을 출시했다고 10일 밝혔다.무좀은 피부사상균에 의해 발생하는 표재성 진균 감염 질환이다. 무좀균은 고온다습한 여름철에 빠르게 증식하는 특성... 2026.07.10 09:05 2 동아쏘시오그룹, 제3회 안전보건협의체 실시…안전보건 역량 강화 동아쏘시오홀딩스는 지난 18일 서울 동대문구 본사에서 ‘제3회 동아쏘시오그룹 안전보건협의체’를 실시했다고 19일 밝혔다.이번 행사에는 동아쏘시오홀딩스, 동아에스티, 동아제약, 에스티팜, 비티젠,... 2026.06.19 08:50 3 누적 기부금만 17억원…동아제약, 사랑나눔바자회 성료 동아제약이 &#39;제15회 동아제약 사랑나눔 바자회&#39;의 수익금 전달식을 가졌다고 5일 밝혔다.수익금 전달식에는 백상환 동아제약 사장과 김영섭 동대문구사회복지협의회 회장 등 관계자들이 참여했다.전달식에서 동아... 2026.06.05 08:55 ADVERTISEMENT 많이 본 뉴스 1 \"자식도 싫다는 회사\"…땅 팔고 폐업 택하자 정부 칼 빼들었다 2026.07.22 17:53 2 품절, 품절, 품절…\"이게 1000원?\" 다이소 또 터졌다 2026.07.21 20:00 3 제주까지 몰려온 어선 1000척…바다 뒤덮",
      "impact": "positive",
      "takeaway": "동아쏘시오홀딩스 사업지주사 전환으로 조직 효율화"
    },
    {
      "s": "연합뉴스",
      "t": "바이오헬스산업 이끌 '보건의료 국가대표기술' 선정·지원",
      "d": "(서울=연합뉴스) 고유선 기자 = 보건복지부는 23일 서울 중구 롯데호텔에서 2026년 제2차 보건의료기술정책심의위원회를 열어 보건의료 국가대표...",
      "u": "https://www.yna.co.kr/view/AKR20260723171700530",
      "m": "07. 23. AM 08:32",
      "ts": 1784795531000,
      "fullText": "보건복지부는 23일 서울 중구 롯데호텔에서 2026년 제2차 보건의료기술정책심의위원회를 열어 보건의료 국가대표기술 30선 선정 계획과 2027년 보건의료 연구개발 투자방향 등을 논의했다고 밝혔다. 이와 별도로 복지부와 질병관리청은 AI 시대 바이오헬스 기술 발전의 핵심 자원인 보건의료 연구데이터가 유용하게 활용될 수 있도록 '보건의료 연구개발사업 연구데이터 공동 관리규정' 제정을 함께 추진하기로 했다. 이형훈 복지부 제2차관은 \"보건의료 국가연구개발사업은 국민 건강과 바이오헬스산업 경쟁력을 동시에 뒷받침하는 핵심 기반\"이라며 \"국가대표기술을 전략적으로 육성하고 연구데이터 활용 기반을 체계적으로 구축해 바이오헬스 강국을 실현하겠다\"고 전했다. 인공지능이 자동으로 줄인 '세 줄 요약' 기술을 사용합니다. 전체 내용을 이해하기 위해서는 기사 본문과 함께 읽어야 합니다.",
      "impact": "positive",
      "takeaway": "보건의료 국가대표기술 선정·지원으로 산업 성장 동력 확보"
    },
    {
      "s": "연합뉴스",
      "t": "아리바이오랩, 20억원 유상증자…아리바이오에 제3자배정",
      "d": "(서울=연합뉴스) 코스닥 상장사 아리바이오랩[261780]은 운영자금 등 약 20억원을 조달하고자 제3자배정 유상증자를 결정했다고 23일 공시했...",
      "u": "https://www.yna.co.kr/view/AKR20260723154000008",
      "m": "07. 23. AM 07:22",
      "ts": 1784791320000,
      "fullText": "(서울=연합뉴스) 코스닥 상장사 아리바이오랩[261780]은 운영자금 등 약 20억원을 조달하고자 제3자배정 유상증자를 결정했다고 23일 공시했다. 주당 2천123원에 신주 94만2천63주(보통주)가 발행된다. 제3자배정 대상자는 주식회사 아리바이오(계열회사, 94만2천63주)다. ※ 이 기사는 연합인포맥스가 제공한 공시 데이터를 토대로 작성됐습니다. 제보는 카카오톡 okjebo <저작권자(c) 연합뉴스, 무단 전재-재배포, AI 학습 및 활용 금지> 2026/07/23 16:22 송고 2026년07월23일 16시22분 송고 #아리바이오랩 댓글 좋아요 슬퍼요 화나요 후속요청 국내 최대 원스톱 콘텐츠 제공 플랫폼 함께 보면 좋은 콘텐츠 by 데이블 광고 함께 읽기 좋은 콘텐츠 Taboola 후원링크 광고 광고 광고 연합 마이뉴스 다양한 주제별 맞춤 추천 뉴스를 제공합니다. 북마크 공유 공유하기 카카오톡 페이스북 X 페이스북 메신저 네이버 밴드 URL 복사 닫기 URL이 복사되었습니다. 댓글 글자크기 본문 글자 크기 조정 폰트 1단계 13px 폰트 2단계 16px 폰트 3단계 18px 폰트 4단계 20px 폰트 5단계 22px 닫기 프린트 제보"
    },
    {
      "s": "연합뉴스",
      "t": "익산시, 반도체·이차전지 투자유치 추진…제3산단 27만㎡ 공급",
      "d": "(익산=연합뉴스) 김진방 기자 = 전북 익산시는 반도체, 이차전지, 식품, 바이오 등 유망 신산업 분야의 기업 유치를 위해 제3 산업단지 27만...",
      "u": "https://www.yna.co.kr/view/AKR20260723114200055",
      "m": "07. 23. AM 05:00",
      "ts": 1784782809000,
      "fullText": "전북 익산시는 반도체, 이차전지, 식품, 바이오 등 유망 신산업 분야의 기업 유치를 위해 제3 산업단지 27만㎡를 추가 공급한다고 23일 밝혔다. 시는 제1·2일반산업단지의 입주 제한 업종을 완화할 계획이다. 제1·2일반산업단지는 입주 업종 제한으로 기업 유치에 어려움을 겪어왔으며, 이로 인한 투자심리 위축 문제도 지속해서 제기돼 왔다. 인공지능이 자동으로 줄인 '세 줄 요약' 기술을 사용합니다. 전체 내용을 이해하기 위해서는 기사 본문과 함께 읽어야 합니다."
    },
    {
      "s": "한경 IT",
      "t": "듀켐바이오, 라디오디앤에스랩스 합병…방사성의약품 CDMO 강화",
      "d": "",
      "u": "https://www.hankyung.com/article/202607230903i",
      "m": "07. 23. AM 12:03",
      "ts": 1784765035000,
      "fullText": "BIO Insight 한경 PREMIUM9 AI를 넘어서는 성공투자 구독하기 AI 추천 뉴스 AI 추천 뉴스 팝업 닫기 듀켐바이오, 라디오디앤에스랩스 합병…방사성의약품 CDMO 강화 입력 2026.07.23 09:03 수정 2026.07.23 09:03 기사 스크랩 기사 스크랩 댓글 댓글 기사 공유 공유 글자크기 조절 글자크기 프린트 프린트 김유림 기자 구독하기 구글 검색 선호 출처로 추가 Google 검색에서 한국경제 기사를 더 자주 볼 수 있습니다. 방사성의약품 분야 권위자 오승준 신임 CTO 선임 듀켐바이오 는 자회사 라디오디앤에스랩스(Radio DNS Labs)와의 합병을 결정했다고 23일 공시를 통해 밝혔다. 이번 합병을 통해 라디오디앤에스랩스 창업자인 오승준 박사가 듀켐바이오의 신임 최고기술책임자(CTO)로 선임된다. 라디오디앤에스랩스는 방사성의약품과 핵의학 영상기술을 연구하는 R&D 전문기업이다. 방사성의약품 분야의 권위자로 손꼽히는 오승준 박사가 창업했으며, 2024년 듀켐바이오가 전체 지분을 인수하면서 자회사로 편입됐다. 이번 합병으로 라디오디앤에스랩스에서 축적해 온 후보물질과 영상기술을 듀켐바이오의 생산, 허가 역량과 한 조직에서 통합 운용하게 됐다. 또한, 듀켐바이오는 방사성의약품 분야 위탁개발생산(CDMO) 사업 착수 단계부터 오 CTO와 함께하기 위해 합병과 동시에 이번 선임을 결정했다. 라디오디앤에스랩스와 공동 착수한 치료용 방사성의약품(RPT) 신약 개발 역시 속도를 높여 사업화와 시장 공략으로 이어간다는 방침이다. 오 CTO는 2008년 파킨슨병 진단용 방사성의약품(18F-FP-CIT)의 신약 허가 전 과정 및 2019년에는 재발, 전이성 대상 유방암 방사성의약품 진단제 &lsquo;18F-FES&rsquo; 개발 전 과정을 수행했다. 또한, 오 CTO는 18F-FP-CIT PET 검사 대기 시간을 단축하기 위해 초기 촬영 데이터만으로 후기 영상을 예측하는 AI 조기영상 예측 기술 등의 공동연구 원천 특허 등록 후, 올해 미국 특허 등록을 완료했다. 듀켐바이오는 이를 PET 검사 현장에 적용하는 상용화를 추진하고 있다. 김상우 듀켐바이오 대표는 &quot;오승준 신임 CTO는 세계 최초 파킨슨병 진단용 방사성의약품의 식약처 신약 품목허가를 시작으로 진단과 치료 목적 약물 개발을 직접 수행한 방사성의약품 분야의 권위자&quot;라고 강조했다. 방사성의약품은 신약 허가 과정에서 제조 공정과 품질 관리 체계가 엄격하게 검토된다. CDMO 고객사가 파트너를 선정할 때 개발과 생산 실적을 우선 고려하는 이유다. 김 대표는 &quot;오 CTO의 합류로 후보물질 개발부터 허가까지 원스톱으로 수행하는 CDMO 역량을 갖추게 됐다&quot;며 &quot;글로벌 RPT 시장이 팽창하면서 CDMO 수요도 급격히 증가하고 있다&quot;고 말했다. 이어 김 대표는 &quot;방사성의약품은 짧은 반감기 탓에 권역별 생산 거점 확보가 필수적인 분야인 만큼, 한국의 지리적 이점을 활용해 중국, 일본, 대만 등을 아우르는 아시아, 태평양 지역의 핵심 공급 거점으로 자리매김하겠다&quot;고 덧붙였다. 그동안 듀켐바이오는 미충족 의료 수요가 큰 분야를 우선순위에 두고, 장기 관점에서 국내에 선례가 없는 계열 내 최초(first-in-class) RPT 파이프라인 구축에 역량을 집중해왔다. 이번 인사를 계기로 미국, 유럽 등 선진 시장을 겨냥한 RPT 신약 포트폴리오 구축에 R&D 투자를 확대해 나가기로 했다. 오승준 CTO는 &quot;라디오디앤에스랩스의 후보물질과 영상기술이 듀켐바이오의 생산, 허가 역량과 만나 하나의 개발 축을 이루게 됐다&quot;며 &quot;개발부터 진단, 치료용 방사성의약품의 생산과 허가까지 잇는 전(全) 주기 통합 R&D 체계를 토대로 자체 RPT 신약과 CDMO 사업의 경쟁력을 끌어올려, 글로벌 방사성의약품 시장에서 기술력으로 인정받는 기업으로 도약하는 데 일조하겠다&quot;고 포부를 밝혔다. 김유림 기자 youforest@hankyung.com 좋아요 싫어요 후속기사 원해요 ⓒ 한"
    },
    {
      "s": "한경 IT",
      "t": "엘앤씨바이오 '메가너브', 대학병원 40여 곳 도입…신경이식재 국산화 확대",
      "d": "",
      "u": "https://www.hankyung.com/article/202607230849i",
      "m": "07. 22. PM 11:50",
      "ts": 1784764215000,
      "fullText": "BIO Insight 한경 PREMIUM9 AI를 넘어서는 성공투자 구독하기 AI 추천 뉴스 AI 추천 뉴스 팝업 닫기 엘앤씨바이오 ‘메가너브’, 대학병원 40여 곳 도입…신경이식재 국산화 확대 입력 2026.07.23 08:50 수정 2026.07.23 08:50 기사 스크랩 기사 스크랩 댓글 댓글 기사 공유 공유 글자크기 조절 글자크기 프린트 프린트 김유림 기자 구독하기 구글 검색 선호 출처로 추가 Google 검색에서 한국경제 기사를 더 자주 볼 수 있습니다. 수화형(Ready-to-Use) 제품으로 사용 편의성 높여 엘앤씨바이오 는 자사의 동종신경이식재 메가너브(MegaNerve)가 국내 주요 대학병원 40여 곳에 도입되며 신경재건 분야에서 국산 치료재료의 적용 범위를 확대하고 있다고 23일 밝혔다. 기존 해외 수입 제품 중심으로 형성돼 온 동종신경이식재 시장에서 국산 제품의 새로운 선택지를 제시하며 의료 현장의 관심을 받고 있다. 메가너브는 신경 결손 부위 재건을 위해 사용하는 인체조직 유래 Nerve ECM(Extracellular Matrix) 기반 동종신경이식재다. 현재 정형외과, 성형외과, 구강악안면외과 등 다양한 진료과에서 활용되고 있으며 디지털신경, 정중신경, 척골신경 등 상지 말초신경 손상을 비롯해 하치조신경 및 설신경 재건, 구강암 절제 후 신경 결손, 안면신경 재건, 신경종 치료 등 다양한 신경재건 분야에 적용되고 있다. 국내 동종신경이식재 시장은 오랜 기간 해외 수입 제품 중심으로 형성돼 왔다. 글로벌 시장에서는 미국 Axogen의 제품이 대표적으로 사용되고 있으나, 냉동 상태로 공급돼 수술 전 해동 과정이 필요하고 신경 결손 길이에 따라 치료재료 비용이 수백만 원에서 많게는 1000만 원 이상 발생하는 경우도 있어 의료기관과 환자 모두에게 부담 요인으로 작용해 왔다. 메가너브는 이러한 사용상의 한계를 개선하기 위해 수화형(Ready-to-Use) 제품으로 개발됐다. 별도의 해동 과정 없이 바로 사용할 수 있어 수술 준비 시간을 단축할 수 있으며, 보관과 사용 과정의 편의성을 높인 것이 특징이다. 특히 엘앤씨바이오는 동종신경이식재의 국산화를 통해 기존 수입 제품 대비 약 40% 낮은 수준의 보험 급여 상한금액을 확보하며 가격 경쟁력을 높였다. 이를통해 고가의 수입 치료재료에 대한 의존도를 낮추고, 보다 많은 환자가 신경재건 치료를 받을 수 있는 환경 조성에 기여하고 있다. 회사 측은 메가너브가 주요 대학병원 40여 곳에 도입된 배경으로 수화형 제품의 높은 사용 편의성, 가격 경쟁력, 안정적인 국내 공급 체계를 꼽았다. 특히 해외 제품 중심이었던 시장에서 국산 동종신경이식재라는 새로운 선택지가 마련되면서 의료진의 활용 범위가 점차 확대되고 있다는 설명이다. 메가너브는 엘앤씨바이오가 구축하고 있는 인체조직 유래 ECM(Extracellular Matrix) 플랫폼의 대표 제품 중 하나다. 엘앤씨바이오는 재건용 ADM ECM 메가덤(MegaDerm), Particle-type ECM 리투오(Re2O), Cartilage ECM 메가카티(MegaCarti), Nerve ECM 메가너브(MegaNerve) 등 다양한 ECM 기반 제품 포트폴리오를 구축하며 재건의료와 미용의료를 아우르는 글로벌 ECM 플랫폼 기업으로 성장하고 있다. 한편 메가너브는 신촌세브란스병원, 삼성서울병원, 서울아산병원, 강남세브란스병원 등 주요 상급종합병원에서 다양한 임상 연구가 진행되고 있으며, 신경재건 분야에서 적응증 확대와 임상적 근거 확보를 위한 연구도 지속적으로 이어지고 있다. 엘앤씨바이오는 해외 수입 제품에 의존해 온 인체조직의 국산화를 통해 환자의 치료비 부담을 낮추고 안정적인 치료재료 공급에 기여하는 등 사회적 가치 창출에도 힘쓰고 있다. 앞으로도 다양한 인체조직 유래 ECM 플랫폼 기술을 바탕으로 국민의 치료 접근성을 높이고, 국내 재건의료 산업의 경쟁력 강화와 글로벌 시장에서 대한민국 인체조직 산업의 위상 제고에 기여해 나갈 계획이다. 김유림 기자 youforest@hankyung.com 좋아요 싫어요 후속"
    },
    {
      "s": "한경 IT",
      "t": "[해외 통신원 리포트]中 제약·바이오 2026 상반기 결산 5대 이슈로 읽는 중국 바이오의 지금",
      "d": "",
      "u": "https://www.hankyung.com/article/202606294647i",
      "m": "07. 22. PM 11:42",
      "ts": 1784763751000,
      "fullText": "BIO Insight 한경 PREMIUM9 AI를 넘어서는 성공투자 구독하기 [해외 통신원 리포트]中 제약·바이오 2026 상반기 결산 5대 이슈로 읽는 중국 바이오의 지금 입력 2026.07.23 08:42 수정 2026.07.23 08:42 기사 스크랩 기사 스크랩 댓글 댓글 기사 공유 공유 글자크기 조절 글자크기 프린트 프린트 구글 검색 선호 출처로 추가 Google 검색에서 한국경제 기사를 더 자주 볼 수 있습니다. 글 이상재 객원기자 2026년 상반기 중국 제약&middot;바이오산업은 격변의 연속이었다. 제약&middot;바이오가 국가 신흥 핵심산업으로 격상되면서 대규모 정책 자금이 유입됐고, AI 신약개발 분야에서는 빅테크의 사업 분사와 조 단위 기술수출 계약이 잇따랐다. 중국산 혁신신약은 연이어 &lsquo;세계 최초&rsquo; 타이틀을 거머쥐었으며, 라이선스아웃 계약 총액은 1분기에만 600억달러를 넘어섰다. 여기에 백신의 의료보험 적용 허용과 항체약물접합체(ADC) 기술의 세대교체까지 맞물리면서 중국 바이오산업이 &lsquo;모방&rsquo;에서 &lsquo;선도&rsquo;로 전환하고 있다는 평가가 나온다. 사진 게티이미지뱅크 ① 바이오의약, 국가 &lsquo;신흥 지주산업&rsquo; 격상&hellip; 정책 자본 대거 유입 2026년 상반기 중국 바이오의약산업은 집적회로, 저공경제(드론&middot;도심항공교통&middot;UAM)와 함께 국가 신흥 지주산업으로 공식 지정됐다. 단순한 명칭 변경이 아니라 세제&middot;금융&middot;토지&middot;인력 전반에 걸친 정책 지원이 뒤따르는 실질적인 지위 격상이다. 좋아요 싫어요 후속기사 원해요 ⓒ 한경닷컴, 무단전재 및 재배포 금지 한국경제 구독신청 한경 프리미엄9 구독신청 앨리스 질문과 답변 더 궁금한 점이 있으신가요? 읽으면서 머릿속에 맴돌던 질문들, 앨리스가 대답해 드릴게요. 1일(현지시간) 제롬 파월 미 연방준비제도(Fed·연준) 의장이 연준의 다음번 금리 변경이 금리 인상은 아니라고 언급한 가운데 뉴욕증시 3대 지수가 혼조로 마감했다. 다른 기업들이 머스크 파운드리 선언에 대해 어떻게 반응하고 있나요? 앨리스 답변 아직 공식 기업들의 공개적인 '머스크 파운드리 선언에 대한 의견 표명' 은 제한적입니다. 반응은 대부분 시장 분석, 전략적 관측, 기술·공급망 논평 등 간접적 형태로 나타나고 있습니다. 삼성·TSMC 등 주요 파운드리 기업은 테슬라의 움직임에 직접적인 '비판'보다는 비즈니스 기회와 경쟁 구도 변화 측면으로 주로 반응하고 있습니다. 글로벌 반도체 빅테크는 자체 제조 확장 계획과 관련해 제조 난이도와 공급망 리스크 측면에서 주목하고 있습니다. 시장 분석가들은 테슬라의 전략이 업계 전반의 파운드리 모델에 변화를 줄 수 있다고 평가하며, 공급망 다변화와 기술 경쟁 강화 가능성을 언급하고 있습니다. --> 머스크 파운드리 선언이 기업에 미치는 영향은? 앨리스 답변 아직 공식 기업들의 공개적인 '머스크 파운드리 선언에 대한 의견 표명' 은 제한적입니다. 반응은 대부분 시장 분석, 전략적 관측, 기술·공급망 논평 등 간접적 형태로 나타나고 있습니다. 삼성·TSMC 등 주요 파운드리 기업은 테슬라의 움직임에 직접적인 '비판'보다는 비즈니스 기회와 경쟁 구도 변화 측면으로 주로 반응하고 있습니다. 글로벌 반도체 빅테크는 자체 제조 확장 계획과 관련해 제조 난이도와 공급망 리스크 측면에서 주목하고 있습니다. 시장 분석가들은 테슬라의 전략이 업계 전반의 파운드리 모델에 변화를 줄 수 있다고 평가하며, 공급망 다변화와 기술 경쟁 강화 가능성을 언급하고 있습니다. 머스크 파운드리 선언이 기술 발전에 미치는 영향은? 앨리스 답변 아직 공식 기업들의 공개적인 '머스크 파운드리 선언에 대한 의견 표명' 은 제한적입니다. 반응은 대부분 시장 분석, 전략적 관측, 기술·공급망 논평 등 간접적 형태로 나타나고 있습니다. 삼성·TSMC 등 주요 파운드리 기업은 테슬라의 움직임에 직접적인 '비판'보다는 비즈니스 기회와 경쟁 구도 변화 측면으로 주로 반"
    },
    {
      "s": "한경 IT",
      "t": "큐리언트, 이중 페이로드 ADC 비임상…엔허투 대비 반응률 우위",
      "d": "",
      "u": "https://www.hankyung.com/article/202607230703i",
      "m": "07. 22. PM 11:15",
      "ts": 1784762110000,
      "fullText": "BIO Insight 한경 PREMIUM9 AI를 넘어서는 성공투자 구독하기 AI 추천 뉴스 AI 추천 뉴스 팝업 닫기 큐리언트, 이중 페이로드 ADC 비임상…엔허투 대비 반응률 우위 입력 2026.07.23 08:15 수정 2026.07.23 08:15 기사 스크랩 기사 스크랩 댓글 댓글 기사 공유 공유 글자크기 조절 글자크기 프린트 프린트 김유림 기자 구독하기 구글 검색 선호 출처로 추가 Google 검색에서 한국경제 기사를 더 자주 볼 수 있습니다. 영장류 반복투여 독성시험을 통해 우수한 안전성 확보 큐리언트 는 미국 보스턴에서 개최된 AACR D3 2026에서 HER2 표적 이중 페이로드 항체약물접합체(ADC) QP101의 비임상 효능 데이터와 비인간 영장류(NHP) 심화 독성 데이터를 공개했다고 23일 밝혔다. AACR D3는 미국암연구학회(AACR)가 항암 신약의 발굴부터 임상 시험까지 개발 전 과정을 학계, 병원, 바이오텍, 글로벌 파마, 투자업계, 규제기관(FDA) 등이 모두 모이는 자리에서 심도 있게 논의하기 위해 올해 처음 개최하는 학술대회로, 주로 신규 모달리티 후보물질 등 최신 개발 동향과 연구개발 성과들이 논의되는 자리다. AACR D3는 7월 21일부터 24일까지(현지시간) 미국 보스턴에서 진행되었으며, 한국 신약개발 기업 중 유일하게 큐리언트가 발표 기관으로 참가했다. 이번 발표에서 큐리언트는 지난 2025년 AACR-NCI-EORTC에서 공개했던 QP101의 전임상 효능 데이터에 더해, 28명의 다양한 HER2 양성 고형암 환자에서 유래한 종양을 이식한 모델(PDX)을 사용해 실제 임상 시험을 시뮬레이션하는 MCT(Mouse Clinical Trial) 결과 및 HER2 초저발현 모델에서 QP101 고용량 투여 결과를 발표하여 주목을 받았다. MCT 결과 QP101은 HER2 양성 고형암 환자 종양 이식 모델(PDX)에서 53.6%의 반응률을 기록해, 동일 용량을 투여한 엔허투(42.9%) 대비 우수한 반응을 보였다. 또한 HER2 초저발현 모델에서 QP101 고용량 투여 효능을 보여 높은 안전성을 기반으로 한 새로운 치료법을 제시했다. 이에 더해 원숭이를 대상으로 진행한 반복 투약 독성시험에서는, 10, 30, 90mg/kg 세 용량군을 3주 간격으로 3회 정맥 투여하여 안전성과 약동학을 확인했다. 실험 결과 투여 용량에 비례한 체내 노출량이 나타났고, 최고용량인 90mg/kg에서도 임상징후, 체중, 혈액학 등 전 항목에 걸쳐 유의미한 독성 소견이 확인되지 않았다. 이를 통해 QP101은 30배를 초과하는 치료지수(TI)를 확보했다. QP101은 트라스투주맙에 TOP1(토포아이소머레이즈1) 저해제와 CDK7 저해제를 각각 두 개씩 결합한 이중 페이로드 ADC다. 서로 다른 기전의 두 약물이 각각 독립적으로 항암 효과를 보이는 동시에 CDK7 저해제가 TOP1 저해제의 민감도를 끌어올려 상승효과를 내는 디자인으로, QP101은 기존 ADC 대비 낮은 항체 당 페이로드 비율(DAR)로도 더 높은 수준의 효능과 넓은 적용 범위를 확보하도록 설계됐다. 이번 발표에서 확인된 효능 및 안전성 데이터는 이러한 설계 전략이 맞아떨어졌음을 보여주며, 엔허투 내성 종양을 포함해 기존 HER2 ADC가 충분히 다루지 못한 영역까지 QP101의 적용 범위를 넓혀 나갈 수 있음을 시사한다. 남기연 큐리언트 대표는 &ldquo;이중 페이로드 ADC 디자인에서는 &lsquo;두 개의 서로 다른 독성 페이로드를 더할 것인가, 서로 시너지를 보이는 두 개의 페이로드를 사용할 것인가&rsquo;를 두고 전략적 선택에 대한 논의가 이어져 왔다&rdquo;며 &ldquo;이번 발표를 통해 QP101은 이 두 가지 전략을 모두 달성할 수 있는 이중 페이로드 ADC라는 것을 보여줬다&rdquo;고 말했다. 이어 &ldquo;가장 혁신적인 신약개발을 지향하는 학회에서 경쟁력이 확인된 만큼, 큐리언트의 이중 페이로드 전략이 부각될 것으로 기대한다&rdquo;고 했다. 김유림 기자 youforest@hankyung.com 좋아요"
    },
    {
      "s": "한경 IT",
      "t": "삼성바이오로직스, 2분기 매출 1조3209억원·영업이익 5864억원 기록",
      "d": "",
      "u": "https://www.hankyung.com/article/202607230687i",
      "m": "07. 22. PM 11:09",
      "ts": 1784761743000,
      "fullText": "BIO Insight 한경 PREMIUM9 AI를 넘어서는 성공투자 구독하기 AI 추천 뉴스 AI 추천 뉴스 팝업 닫기 삼성바이오로직스, 2분기 매출 1조3209억원·영업이익 5864억원 기록 입력 2026.07.23 08:09 수정 2026.07.23 08:36 기사 스크랩 기사 스크랩 댓글 댓글 기사 공유 공유 글자크기 조절 글자크기 프린트 프린트 김유림 기자 구독하기 구글 검색 선호 출처로 추가 Google 검색에서 한국경제 기사를 더 자주 볼 수 있습니다. 전년 동기 대비 30%, 23% 증가 1~4공장 Full 가동 및 우호적 환율 영향 연간 매출 성장률 가이던스 상단 달성 전망 삼성바이오로직스 는 23일 공시를 통해 올해 2분기 매출 1조3209억원, 영업이익 5864억원을 기록했다고 밝혔다. AI 기반 투자정보 플랫폼 에픽AI가 집계한 삼성바이오로직스의 2분기 실적 컨센서스는 매출 1조3273억원, 영업이익 5940억원이다. 실제 매출과 영업이익은 시장 예상치에 대체로 부합했다. 2분기 매출은 전년 동기 대비 3067억원(30%), 영업이익은 1092억원(23%) 증가했다. 1~4공장의 풀(Full) 가동 효과와 우호적인 환율의 영향으로 전년 동기 대비 견조한 성장세를 이어갔다. 영업이익률은 5공장 및 미국 록빌 생산시설의 본격적인 매출 인식에 앞서 관련 비용이 선반영 되었음에도 40%대를 유지했다. 삼성바이오로직스는 2분기 일부 배치 생산 차질에도 불구하고 5공장과 미국 록빌 생산시설의 매출 기여 확대, 우호적인 환율 등을 바탕으로 2026년 연간 매출 성장률 가이던스(전년 대비 +15~20%)의 상단 달성이 가능할 것으로 전망하고 있다. 한편, 삼성바이오로직스의 2026년 2분기 말 기준 자산은 12조6,526억원, 자본은 8조3,619억원, 부채는 4조2,907억원이다. 부채비율은 51.3%, 차입금 비율은 11.5%로 안정적인 재무구조를 유지하고 있다. 삼성바이오로직스는 위탁생산(CMO) 및 위탁개발(CDO) 전 분야에서 수주 활동을 지속하고 있다. 창립 이래 누적 수주는 CMO 115건, CDO 176건이며, 누적 수주 총액은 217억 달러를 기록 중이다. 글로벌 거점 측면에서는 3분기 내 네덜란드에 유럽 세일즈 오피스를 개소하여 글로벌 시장 공략을 가속화할 예정이다. 2023년 미국 뉴저지, 2025년 일본 도쿄에 이어 2026년 네덜란드 암스테르담까지 세일즈 오피스를 확대함으로써 글로벌 바이오의약품 3대 시장으로 꼽히는 미국, 유럽, 일본 및 아태(APAC) 지역까지 영업 거점을 확보하게 된다. 이를 기반으로 수주 경쟁력을 강화하고, 글로벌 네트워크 확대를 통한 초격차 경쟁력 달성을 지속해 나갈 계획이다. 포트폴리오 측면에서는 글로벌 펩타이드 CDMO 기업 폴리펩타이드그룹 인수를 결정하는 등 사업 영역을 지속적으로 확장해오고 있다. 삼성바이오로직스는 주력 사업인 항체의약품 외에도 메신저 리보핵산(mRNA), 항체&middot;약물접합체 (ADC)등 다양한 신규 모달리티 개발&middot;생산 역량을 확보하는 한편, 고부가가치 신규 모달리티 생산시설 구축을 위한 제3바이오캠퍼스 부지를 확보했다. 삼성바이오로직스는 다우존스 베스트 인 클래스 월드지수((DJBIC)에 5년 연속 편입돼 글로벌 최고 수준의 ESG 관리 역량을 다시한번 인정받았으며, 2026 ESG 보고서도 발간하는 등 ESG경영 측면에서도 이해관계자의 신뢰를 바탕으로 지속가능한 성장을 이어갈 방침이다. 김유림 기자 youforest@hankyung.com 좋아요 싫어요 후속기사 원해요 ⓒ 한경닷컴, 무단전재 및 재배포 금지 한국경제 구독신청 한경 프리미엄9 구독신청 김유림 ADVERTISEMENT 관련 뉴스 1 큐리언트, 이중 페이로드 ADC 비임상…엔허투 대비 반응률 우위 큐리언트는 미국 보스턴에서 개최된 AACR D3 2026에서 HER2 표적 이중 페이로드 항체약물접합체(ADC) QP101의 비임상 효능 데이터와 비인간 영장류(NHP) 심화 독성 데이터를 공개했다고 23일 밝혔다.... 2026.07.23 08:15 2 삼성"
    },
    {
      "s": "한경 IT",
      "t": "아리바이오 치매 치료제 11월 학회서 3상 구두발표",
      "d": "",
      "u": "https://www.hankyung.com/article/2026072200141",
      "m": "07. 22. AM 08:40",
      "ts": 1784709641000,
      "fullText": "BIO Insight 한경 PREMIUM9 AI를 넘어서는 성공투자 구독하기 AI 추천 뉴스 AI 추천 뉴스 팝업 닫기 아리바이오 치매 치료제 11월 학회서 3상 구두발표 입력 2026.07.22 17:40 수정 2026.07.23 01:17 지면 A16 기사 스크랩 기사 스크랩 댓글 댓글 기사 공유 공유 글자크기 조절 글자크기 프린트 프린트 최지희 기자 구독하기 구글 검색 선호 출처로 추가 Google 검색에서 한국경제 기사를 더 자주 볼 수 있습니다. 아리바이오는 치매를 일으키는 알츠하이머병 치료제 &lsquo;AR1001&rsquo;의 글로벌 임상 3상 결과를 오는 11월 16일 제19회 알츠하이머병 임상시험 학회(CTAD 2026)에서 구두로 발표한다고 22일 밝혔다. CTAD 2026은 16일부터 19일까지 미국 보스턴에서 열린다. 아리바이오는 초기 알츠하이머병 환자 1535명을 대상으로 13개국 약 230개 임상센터에서 글로벌 임상 3상을 진행했다. 정재준 아리바이오 대표는 &ldquo;개막일 첫 구두발표 채택은 학계의 높은 관심도를 반영한 결과&rdquo;라며 &ldquo;톱라인(주요 결과)은 학회 전에 결과가 나오는 즉시 공개하겠다&rdquo;고 말했다. 이어 &ldquo;CTAD에서 주요 유효성&middot;안전성 지표와 세부 분석 결과가 발표되면 이를 기반으로 글로벌 규제기관 협의 및 신약허가 신청 준비를 추진할 것&rdquo;이라고 했다. 최지희 기자 mymasaki@hankyung.com 좋아요 싫어요 후속기사 원해요 ⓒ 한경닷컴, 무단전재 및 재배포 금지 한국경제 구독신청 한경 프리미엄9 구독신청 최지희 ADVERTISEMENT 관련 뉴스 1 아리바이오 \"먹는 국산 치매약 시대 연다\" 아리바이오가 먹는 국산 알츠하이머 치매 신약을 개발하기 위한 과학적 근거를 쌓아가고 있다. 미국, 유럽, 한국 등에서 시행 중인 글로벌 임상시험에서 기존 항체 신약과 비슷한 효과를 낼 가능성이 높다는 중간 분석 결과... 2025.08.25 16:51 2 아리바이오·소룩스 합병 표류…中 치매약 판매 실체 불확실 코스닥 시장에 상장한 조명기기 업체 소룩스와 합병을 통해 코스닥 입성을 추진하고 있는 바이오 회사 아리바이오가 난관을 만났다. 지난해 8월 합병 계획을 공식화했으나 이후 금융감독원으로부터 6차례에 걸쳐 정정 요구를 ... 2025.07.14 15:54 3 아리바이오 \"머리에 쓰면 치매 관리에 도움\" 세계 최초로 음향과 진동으로 두뇌를 자극해 치매 관리에 도움을 주는 건강관리기기가 국내에 출시된다.아리바이오는 두뇌 건강관리기기 ‘헤르지온’을 이달 말 국내에 출시한다고 15일 밝혔다. 장수산업... 2024.05.15 17:38 ADVERTISEMENT 많이 본 뉴스 1 품절, 품절, 품절…\"이게 1000원?\" 다이소 또 터졌다 2026.07.21 20:00 2 이런 직업도 있었어?…\"월 800만원 번다\" 한국서 수요 폭발 2026.07.22 06:00 3 주진우 \"우원식, 82억 들인 해외출장 14회 모두 배우자 동행\" 2026.07.21 15:16 4 \"대표도 장관도 다 고발\"…삼전닉스 돈잔치, 터질 게 터졌다 2026.07.22 13:49 5 삼전 내년 821조 돈방석 앉는다…S&P 역대급 전망에 술렁 2026.07.22 09:37 ADVERTISEMENT 이 시각 관심정보 AD ADVERTISEMENT --> ADVERTISEMENT ADVERTISEMENT"
    },
    {
      "s": "한경 IT",
      "t": "[포토] 삼성바이오에피스·서울시, 유망 바이오텍 지원",
      "d": "",
      "u": "https://www.hankyung.com/article/2026072200111",
      "m": "07. 22. AM 08:39",
      "ts": 1784709592000,
      "fullText": "BIO Insight 한경 PREMIUM9 AI를 넘어서는 성공투자 구독하기 AI 추천 뉴스 AI 추천 뉴스 팝업 닫기 [포토] 삼성바이오에피스·서울시, 유망 바이오텍 지원 입력 2026.07.22 17:39 수정 2026.07.23 01:20 지면 A16 기사 스크랩 기사 스크랩 댓글 댓글 기사 공유 공유 글자크기 조절 글자크기 프린트 프린트 구글 검색 선호 출처로 추가 Google 검색에서 한국경제 기사를 더 자주 볼 수 있습니다. 삼성바이오에피스와 서울시, 서울바이오허브 관계자들이 22일 인천 송도 삼성바이오에피스 사옥에서 &lsquo;2026 서울바이오허브-삼성바이오에피스 오픈이노베이션 프로그램&rsquo; 협약식을 가졌다. 삼성바이오에피스 제공 좋아요 싫어요 후속기사 원해요 ⓒ 한경닷컴, 무단전재 및 재배포 금지 한국경제 구독신청 한경 프리미엄9 구독신청 ADVERTISEMENT 관련 뉴스 1 '세계 1위 의약품' 키트루다…삼성에피스, 동등성 입증 삼성바이오에피스가 세계 매출 1위 의약품인 미국 머크(MSD)의 ‘키트루다’ 바이오시밀러(바이오의약품 복제약) 시장 진출 속도를 높이고 있다. 바이오시밀러 개발 기업 중 처음으로 대규모 임상시험... 2026.06.29 18:30 2 삼성에피스·지투지바이오…비만치료제 공동 개발 삼성바이오에피스가 국내 바이오벤처 기업 지투지바이오에서 비만치료제 신약 후보물질(파이프라인)을 도입했다. 에피스넥스랩은 지투지바이오와 함께 장기지속형 약물 플랫폼을 만들기 위한 공동 연구를 한다.삼성바이오에피스 등은... 2026.03.16 17:07 3 삼성바이오에피스, 특허 합의…유럽서 망막치료제 연내 출시 삼성바이오에피스가 유럽 등에서 망막질환 치료제 아일리아의 바이오시밀러(바이오의약품 복제약) ‘SB15’를 출시할 수 있게 됐다.삼성바이오에피스는 아일리아의 오리지널 개발사인 미국 리제네론, 독일... 2026.01.30 17:05 ADVERTISEMENT 많이 본 뉴스 1 품절, 품절, 품절…\"이게 1000원?\" 다이소 또 터졌다 2026.07.21 20:00 2 이런 직업도 있었어?…\"월 800만원 번다\" 한국서 수요 폭발 2026.07.22 06:00 3 주진우 \"우원식, 82억 들인 해외출장 14회 모두 배우자 동행\" 2026.07.21 15:16 4 \"대표도 장관도 다 고발\"…삼전닉스 돈잔치, 터질 게 터졌다 2026.07.22 13:49 5 삼전 내년 821조 돈방석 앉는다…S&P 역대급 전망에 술렁 2026.07.22 09:37 ADVERTISEMENT 이 시각 관심정보 AD ADVERTISEMENT --> ADVERTISEMENT ADVERTISEMENT"
    },
    {
      "s": "한경 IT",
      "t": "삼성바이오에피스, 인투셀과 ADC 1종 본계약 체결",
      "d": "",
      "u": "https://www.hankyung.com/article/202607229810i",
      "m": "07. 22. AM 07:40",
      "ts": 1784706054000,
      "fullText": "BIO Insight 한경 PREMIUM9 AI를 넘어서는 성공투자 구독하기 AI 추천 뉴스 AI 추천 뉴스 팝업 닫기 삼성바이오에피스, 인투셀과 ADC 1종 본계약 체결 입력 2026.07.22 16:40 수정 2026.07.22 16:40 기사 스크랩 기사 스크랩 댓글 댓글 기사 공유 공유 글자크기 조절 글자크기 프린트 프린트 최지희 기자 구독하기 구글 검색 선호 출처로 추가 Google 검색에서 한국경제 기사를 더 자주 볼 수 있습니다. 삼성바이오에피스가 인투셀과 항체약물접합체(ADC) 신약 후보물질 &#39;SBE303&#39;의 후속 연구개발과 상업화를 위한 계약을 체결했다고 밝혔다. 이번 계약은 양사가 공동연구를 통해 개발한 후보물질의 상업화 권리를 확보하기 위한 후속 계약이다. 삼성에피스홀딩스는 자회사 삼성바이오에피스가 인투셀과 Nectin-4 단백질 표적 고형암 치료제 후보물질 SBE303의 연구개발 및 상업화 계약을 체결했다고 22일 공시했다. 공시에 따르면 이번 계약은 2023년 양사가 체결한 최대 5종 ADC 신약 후보물질 발굴 공동연구 계약의 후속 계약이다. 공동연구를 통해 도출된 SBE303의 후속 개발과 상업화를 추진하기 위해 물질 권리를 확보하는 것을 목적으로 하고 있다. SBE303은 인투셀이 보유한 OHPAS 링커 기술 등을 활용해 공동 개발한 Nectin-4 표적 고형암 치료제 후보물질이다. 현재 고형암 환자 149명을 대상으로 글로벌 임상 1상이 이뤄지고 있다. 계약 기간은 국가별 로열티 지급 기간 종료일까지다. 계약에는 이미 지급된 임상 1상 개시 관련 금액과 함께 향후 임상 진전 및 품목허가에 따른 개발 마일스톤, 제품 판매 마일스톤, 매출에 연동된 로열티 지급 조항이 포함됐다. 전체 계약 규모와 세부 조건은 양사 합의에 따라 공개하지 않았다. 삼성바이오에피스는 &ldquo;이번 계약은 조건부 계약으로, 임상시험과 품목허가 성공 여부에 따라 비용 또는 수익 인식이 달라질 수 있다&rdquo;먀 &ldquo;규제기관의 연구개발 중단이나 품목허가 실패 등의 경우 계약이 해지될 수 있다&rdquo;고 공시했다. 김경아 삼성바이오에피스 사장은 &ldquo;이번 계약은 삼성바이오에피스가 국내 기업과의 협력을 통해 차세대 항암제 분야로 사업 영역을 확장하는 중요한 이정표&rdquo;라며 &ldquo;앞으로도 다양한 의료 미충족 수요 해소를 위한 연구개발 혁신을 지속하겠다&quot;고 밝혔다. 박태교 인투셀 대표는 &quot;양 사 협업을 통해 인투셀의 링커 플랫폼 기술이 글로벌 시장에서 의미 있는 성과를 창출할 수 있기를 기대한다&quot;고 밝혔다. 최지희 기자 mymasaki@hankyung.com 좋아요 싫어요 후속기사 원해요 ⓒ 한경닷컴, 무단전재 및 재배포 금지 한국경제 구독신청 한경 프리미엄9 구독신청 최지희 ADVERTISEMENT 관련 뉴스 1 티움바이오 “경구용 TU2218로 두경부암 치료 새 선택지 만들 것” “주사제 중심 기존 치료의 한계를 넘어설 가능성을 확인했습니다. 편의성과 약가 경쟁력을 갖춘 먹는 항암신약 TU2218(토스포서팁)로 세계 두경부암 환자에게 새 치료 선택지를 제공하겠습니다.”김... 2026.07.22 15:36 2 심지연 서울아산병원 교수 “비보존 '어나프라', 마약성 진통제 사용 줄일 대안” “수술 후 오피오이드를 하루나 이틀 사용한다고 일반적으로 중독이 생기지는 않습니다. 전신마취 직후 의료진이 더 경계하는 문제는 호흡 억제입니다.”심지연 서울아산병원 마취통증의학과 교수는 20일 ... 2026.07.22 15:22 3 'AI 대명사' 챗GPT 앞질렀다…1년만에 결제액 20배 폭증한 AI 정체 [테크로그] 국내 생성형 인공지능(AI) 유료 결제 시장에서 앤트로픽의 &#39;클로드&#39;가 오픈AI의 &#39;챗GPT&#39;를 처음 앞질렀다. 법인카드 결제와 고가 요금제 수요가 빠르게 늘면서 올해 2분기 결제액 기준... 2026.07.22 15:18 ADVERTISEMENT 많이 본 뉴스 1 품절, 품절, 품절…\"이게 1000원?\" 다이소"
    },
    {
      "s": "NVIDIA공식",
      "t": "Bristol Myers Squibb Building Life Science Industry’s Most Advanced AI Factory on NVIDIA Vera Rubin",
      "d": "Erin Davis calls it the “SuperDuperPOD.” That’s two things in one name: pharmaceutical giant Bristol Myers Squibb (BMS) already runs one of the largest AI clusters in life sciences, with serious results to show for it. And they’re doubling down. BMS announced today it is deploying its second NVIDIA DGX SuperPOD, this one built on [&#8230;]",
      "u": "https://blogs.nvidia.com/blog/bristol-myers-squibb-building-life-science-industrys-most-advanced-ai-factory-on-nvidia-vera-rubin/",
      "m": "07. 20. AM 10:59",
      "ts": 1784545163000,
      "fullText": "Bristol Myers Squibb Building Life Science Industry’s Most Advanced AI Factory on NVIDIA Vera Rubin The pharmaceutical company has demonstrated how AI can transform drug discovery and is now scaling AI across R&D to accelerate the discovery of next-generation medicines. July 20, 2026 by Brian Caulfield 0 Comments Share Share This Article X Facebook LinkedIn Copy link Link copied! Erin Davis calls it the “SuperDuperPOD.” That’s two things in one name: pharmaceutical giant Bristol Myers Squibb (BMS) already runs one of the largest AI clusters in life sciences, with serious results to show for it. And they’re doubling down. BMS announced today it is deploying its second NVIDIA DGX SuperPOD , this one built on eight DGX Vera Rubin NVL72 systems — the most powerful and energy-efficient AI cluster in life sciences. “Instead of equipping a small group of researchers with access to the supercomputer, we’re opening it up to literally every scientist,” says Davis, vice president of research business insights and technology at BMS. “No one has to wait, and no one is told they have a limit.” The eight rack-scale systems, each comprising NVIDIA Vera CPUs and Rubin GPUs, deliver up to 10x the performance per megawatt of the infrastructure it replaces. It will give researchers at the global pharmaceutical giant access to a unified AI platform — including NVIDIA BioNeMo Agent Toolkit for biological AI — for running predictions, training models and powering agentic workflows across the full drug discovery pipeline. What Davis and other top BMS researchers are really after is what that access makes possible: faster cycles, bigger chemical spaces and a full drug discovery pipeline where researchers think about the science, not the logistics of lining up resources. The mandate, says Payal Sheth — a scientist who spent her career inside drug discovery labs before taking on an expanded role in January as senior vice president of therapeutic discovery sciences at BMS — is moving from “sor"
    }
  ]
}