{
  "updatedAt": "2026-07-15T16:18:29.863Z",
  "count": 2,
  "stats": {
    "today": 2,
    "yesterday": 0,
    "weekAvg": 0.3,
    "sources": 1,
    "heat": "cool"
  },
  "items": [
    {
      "s": "한국경제",
      "t": "젠슨 황 \"하이닉스 ADR, 믿을 수 없을 정도로 성공적\"",
      "d": "",
      "u": "https://www.hankyung.com/article/2026071579381",
      "m": "07. 15. PM 01:38",
      "ts": 1784122732000,
      "fullText": "산업 한경 PREMIUM9 AI를 넘어서는 성공투자 구독하기 AI 추천 뉴스 AI 추천 뉴스 팝업 닫기 젠슨 황 \"하이닉스 ADR, 믿을 수 없을 정도로 성공적\" 입력 2026.07.15 22:38 수정 2026.07.15 22:39 지면 A12 기사 스크랩 기사 스크랩 댓글 댓글 기사 공유 공유 글자크기 조절 글자크기 프린트 프린트 강해령 기자 구독하기 구글 검색 선호 출처로 추가 Google 검색에서 한국경제 기사를 더 자주 볼 수 있습니다. 나스닥 안착에 공개적 호평 AI생태계에 긍정적 효과 기대 젠슨 황 엔비디아 최고경영자(CEO&middot;사진)가 SK하이닉스의 미국주식예탁증서(ADR) 나스닥 상장에 관해 &ldquo;믿을 수 없을 정도로 성공적&rdquo;이라고 평가했다. 젠슨 황은 15일 일본 도쿄에서 열린 엔비디아와 일본 대표 게임업체 세가의 파트너십 30주년 기념행사에 참석해 이같이 말했다. 엔비디아에 고대역폭메모리(HBM)를 공급하는 핵심 협력사인 SK하이닉스가 ADR 상장으로 자금을 확보하면 자사 인공지능(AI) 생태계 확대에 도움이 될 것이라는 견해를 밝혔다는 평가다. SK하이닉스 ADR은 지난 10일 공모가 149달러로 미국 나스닥시장에 상장했다. 이번 상장으로 조달한 자금은 265억700만달러(약 40조원)가량이다. 상장을 통해 확보한 자금은 AI 반도체 경쟁력을 높이기 위한 설비 투자에 집중적으로 사용할 계획이다. 젠슨 황은 16일 일본 정부와 함께 대규모 AI 협력 방안을 발표할 예정이다. 그는 &ldquo;16일은 일본 AI의 시작점이라고 할 수 있다&rdquo;며 &ldquo;AI 및 로보틱스 분야에서 다각도의 협력 방안을 발표할 계획&rdquo;이라고 말했다. 1990년대 중반 파산 위기에 처한 엔비디아가 세가에서 500만달러(약 75억원)를 유치한 일화를 언급하며 감사의 뜻을 나타내기도 했다. 강해령 기자 hr.kang@hankyung.com 좋아요 싫어요 후속기사 원해요 ⓒ 한경닷컴, 무단전재 및 재배포 금지 한국경제 구독신청 한경 프리미엄9 구독신청 강해령 ADVERTISEMENT 관련 뉴스 1 애플 12년간 시총 1위…2년전부터 엔비디아 천하 마이크로소프트부터 엔비디아까지 2000년 이후 미국 뉴욕증시의 대장주 변천사는 시기별로 가장 많은 자본을 투입하고 있는 주도 기술과 산업이 무엇인지를 시사한다.2000년 닷컴 버블 붕괴 직후까지 뉴욕증시 시가총액 1... 2026.07.10 17:30 2 삼성전자, 엔비디아에 차세대 AI용 SSD 공급 삼성전자가 차세대 인공지능(AI) 서버에 최적화한 기업용 저장장치(SSD)를 엔비디아에 공급한다. 최근 AI 연산이 급증하면서 데이터 처리 속도가 빠른 고대역폭메모리(HBM)뿐 아니라 저장용량이 큰 낸드플래시와 SS... 2026.07.08 17:32 3 \"고성능 AI 인프라 판다\"…올해 주가 2.5배 뛴 AMD 한국경제신문의 투자 전문 유료 플랫폼 &#39;한경 프리미엄9&#39;(www.hankyung.com/premium9)에 실린 기사입니다. &#39;한경 프리미엄9&#39;을 구독하시면 더 많은 美 주식 투자 기사를... 2026.07.07 17:26 ADVERTISEMENT 많이 본 뉴스 1 \"에어컨 사러 매장 가지 마세요\"…삼성전자, 3700억 쓸어 담았다 2026.07.14 14:48 2 너무 예뻐서 '방송 사고'…'월드컵 여신' 중계로 경기 놓쳤다 2026.07.14 08:31 3 '유재석이 타더니'…7600만원짜리 車, 3000만원대로 산다 2026.07.14 10:32 4 \"쓰레기인 줄 알았는데\"…MZ들 '영수증'에 꽂힌 뜻밖의 이유 2026.07.13 21:00 5 한국도 일본도 막혔다…\"참치 넘쳐나도 버려야 할 판\" 발 동동 2026.07.15 12:56 ADVERTISEMENT 이 시각 관심정보 AD ADVERTISEMENT --> ADVERTISEMENT ADVERTISEMENT",
      "impact": "positive",
      "takeaway": "하이닉스 ADR 성공이 AI 반도체 수요 확대 기대"
    },
    {
      "s": "한국경제",
      "t": "\"믿을 수 없을 정도\"…일본서 'SK하이닉스' 샤라웃한 젠슨황",
      "d": "",
      "u": "https://www.hankyung.com/article/2026071578557",
      "m": "07. 15. AM 11:22",
      "ts": 1784114570000,
      "fullText": "산업 한경 PREMIUM9 AI를 넘어서는 성공투자 구독하기 AI 추천 뉴스 AI 추천 뉴스 팝업 닫기 \"믿을 수 없을 정도\"…일본서 'SK하이닉스' 샤라웃한 젠슨황 입력 2026.07.15 20:22 수정 2026.07.15 20:48 기사 스크랩 기사 스크랩 댓글 댓글 기사 공유 공유 글자크기 조절 글자크기 프린트 프린트 박수빈 기자 구독하기 구글 검색 선호 출처로 추가 Google 검색에서 한국경제 기사를 더 자주 볼 수 있습니다. 日게임업체 협력 이벤트 참가차 방일 &quot;16일 日정부와 AI 협력 발표&quot; 사진=AP 젠슨 황 엔비디아 최고경영자(CEO)가 15일 SK하이닉스가 미국주식예탁증서(ADR)를 나스닥에 상장한 데 대해 호평했다. 황 CEO는 &quot;믿을 수 없을 정도로 성공적(Incredibly Successful)&quot;이라고 말하기도 했다. 황 CEO는 이날 일본 도쿄 아키하바라에서 엔비디아와 일본 게임 회사 세가(SEGA)의 파트너십 30주년 기념 이벤트에 참석했다. 이후 SK하이닉스의 ADR 나스닥 상장에 대한 의견을 묻는 연합뉴스 질의에 이같이 대답하면서 &quot;매우 기쁘다&quot;라고 했다. SK하이닉스는 엔비디아에 인공지능(AI) 반도체 핵심 부품인 고성능 HBM(고대역폭 메모리)을 공급하는 핵심 파트너다. SK하이닉스의 ADR 나스닥 상장에 따른 투자금 유입이 엔비디아의 AI 생태계 확장에도 청신호라는 생각을 황 CEO가 밝힌 것으로 풀이된다. SK하이닉스 ADR은 상장 후 3거래일째인 14일(현지시간) 저평가 인식이 확산해 27.29% 올랐다. 아울러 황 CEO는 오는 16일 일본 정부와 대규모 AI 협력에 대해 발표할 계획이라고도 알렸다. 그는 &quot;내일은 일본 AI의 시작점이라고 할 수 있다&quot;며 일본 대기업들과 AI, 로보틱스 분야에서 다각도의 협력을 발표할 계획이라고 말했다. 황 CEO는 최근 두 차례 한국을 방문했다. 그러면서 일본은 &#39;패싱&#39;했다는 논란을 빚기도 했다. 그런 그가 최근 AI 저변 확대에 힘을 쏟고 있는 다카이치 사나에 내각 및 일본 제조 대기업들과 AI 협력을 준비해온 것으로 보인다. 황 CEO는 이날 세가와 파트너십 30주년 이벤트에서 사토미 하루노리 세가 CEO와 이리마지리 쇼이치로 전 사장, &#39;버추어 파이터&#39; 개발자 스즈키 유 등과 만났다. 이어 3D 그래픽을 선도한 일본 게임업계가 없었다면 엔비디아와 지금의 AI 기술도 없었을 것이라고 올려세웠다. 그는 창업 초기인 1990년대 중반 세가로부터 받았던 500만달러(약 75억3000만원) 규모 투자 일화를 공개해 파산 위기에서 벗어나게 해준 은혜를 입었다고 감사의 뜻을 표했다. 박수빈 한경닷컴 기자 waterbean@hankyung.com 좋아요 싫어요 후속기사 원해요 ⓒ 한경닷컴, 무단전재 및 재배포 금지 한국경제 구독신청 한경 프리미엄9 구독신청 박수빈 ADVERTISEMENT 관련 뉴스 1 \"나스닥 가자\" 10만명 몰렸다…서학개미, SK하닉 4000억 베팅 SK하이닉스가 미국주식예탁증서(ADR)를 상장한 첫날 국내 개인투자자들이 수천억원어치를 사들인 것으로 나타났다. 국내 증시에서도 1조원 넘게 순매수했다. 미국과 한국 시장 양쪽에서 SK하이닉스 주가 상승에 베팅한 셈... 2026.07.15 06:24 2 SK하이닉스, 美 ADR도 9.3% 하락…공모가 소폭 웃돌아 SK하이닉스의 미국주식예탁증서(ADR)가 정식 거래 이틀째인 13일(현지시간) 9% 넘게 떨어지며 거래를 마쳤다.SK하이닉스 ADR은 이날 뉴욕증시에서 전 거래일 대비 9.32% 내린 152.35달러로 장을 마감했다... 2026.07.14 07:21 3 \"한국선 '삼쏘', 왜 안 오나\"…젠슨 황, '재팬 패싱' 논란 끝낸다 최근 한국을 잇달아 찾으면서도 일본은 방문하지 않아 소위 &#39;재팬 패싱&#39; 논란을 빚었던 젠슨 황 엔비디아 최고경영자(CEO)가 조만간 도쿄를 찾는다.13일 엔비디아 지포스 재팬의 엑스(X·옛... 2026.07.13 14:02 ADVER",
      "impact": "positive",
      "takeaway": "일본 투자자들의 SK하이닉스 호평이 AI 칩 성장 기대감 강화"
    }
  ]
}