{
  "updatedAt": "2026-06-11T16:51:42.967Z",
  "related": [
    {
      "slug": "젠슨황",
      "name": {
        "ko": "젠슨 황",
        "en": "Jensen Huang"
      },
      "icon": "🕴️",
      "tier": "hot",
      "overlap": 4
    },
    {
      "slug": "삼성전자",
      "name": {
        "ko": "삼성전자",
        "en": "Samsung Electronics"
      },
      "icon": "📱",
      "tier": "hot",
      "overlap": 4
    },
    {
      "slug": "엔비디아",
      "name": {
        "ko": "엔비디아",
        "en": "NVIDIA"
      },
      "icon": "🟩",
      "tier": "hot",
      "overlap": 3
    },
    {
      "slug": "AI반도체",
      "name": {
        "ko": "AI 반도체",
        "en": "AI Semiconductor"
      },
      "icon": "⚡",
      "tier": "hot",
      "overlap": 3
    }
  ],
  "summary": "삼성전자, AI 혁신을 위한 외부 생성형 AI 전면 도입을 발표했다. 샘 올트먼 오픈AI 최고경영자(CEO)는 방한하여 삼성전자, 네이버, 카카오 경영진을 만났다.",
  "sentiment": "bullish",
  "key_drivers": [
    "삼성전자 AI 혁신",
    "외부 생성형 AI 도입",
    "샘 올트먼 방한"
  ],
  "watch_points": [
    "삼성전자 AI 기술 개발",
    "네이버, 카카오와의 협력",
    "AI 시장 점유율"
  ],
  "risks": [
    "AI 기술 개발 난관",
    "경쟁사와의 기술 격차"
  ],
  "events": [
    {
      "date": "2026-06-11",
      "title": "삼성전자, 외부 생성형 AI 전면 도입",
      "impact": "positive"
    }
  ],
  "key_players": [
    "삼성전자",
    "네이버",
    "카카오",
    "엔비디아",
    "TSMC",
    "마이크론"
  ],
  "outlook": {
    "short_term": {
      "thesis": "삼성전자 AI 혁신이 시장에 긍정적인 영향을 미칠 것으로 예상된다. 외부 생성형 AI 도입이 경쟁사와의 기술 격차를 줄일 것으로 보인다.",
      "upside": "삼성전자 AI 기술 개발이 시장 점유율을 높일 것으로 예상된다.",
      "downside": "AI 기술 개발 난관이 시장에 부정적인 영향을 미칠 것으로 예상된다."
    },
    "mid_term": {
      "thesis": "삼성전자 AI 혁신이 시장에 긍정적인 영향을 미칠 것으로 예상된다. 네이버, 카카오와의 협력이 시장 점유율을 높일 것으로 보인다.",
      "upside": "삼성전자 AI 기술 개발이 시장 점유율을 높일 것으로 예상된다.",
      "downside": "AI 기술 개발 난관이 시장에 부정적인 영향을 미칠 것으로 예상된다."
    },
    "long_term": {
      "thesis": "삼성전자 AI 혁신이 시장에 긍정적인 영향을 미칠 것으로 예상된다. AI 시장 점유율이 높아질 것으로 보인다.",
      "upside": "삼성전자 AI 기술 개발이 시장 점유율을 높일 것으로 예상된다.",
      "downside": "AI 기술 개발 난관이 시장에 부정적인 영향을 미칠 것으로 예상된다."
    }
  },
  "capital_flow": {
    "summary": "외국인·기관 순매수, ETF 자금 유입",
    "signals": [
      "미래에셋 스페이스X 2차 청약 완판"
    ]
  },
  "scenarios": [
    {
      "case": "기본(Base)",
      "probability": 60,
      "thesis": "삼성전자 AI 혁신이 시장에 긍정적인 영향을 미칠 것으로 예상된다.",
      "trigger": "외부 생성형 AI 도입",
      "watch_period": "1~2주"
    },
    {
      "case": "강세(Bull)",
      "probability": 20,
      "thesis": "삼성전자 AI 기술 개발이 시장 점유율을 높일 것으로 예상된다.",
      "trigger": "AI 시장 점유율 50% 돌파",
      "watch_period": "기간"
    },
    {
      "case": "약세(Bear)",
      "probability": 20,
      "thesis": "AI 기술 개발 난관이 시장에 부정적인 영향을 미칠 것으로 예상된다.",
      "trigger": "AI 기술 개발 난관",
      "watch_period": "기간"
    }
  ],
  "pb_perspective": {
    "valuation_assessment": "삼성전자 AI 혁신이 시장에 긍정적인 영향을 미칠 것으로 예상된다. PER/PBR + 동종업계/과거 대비 평가",
    "momentum_signals": "외국인/기관 수급·모멘텀·신고가 근접",
    "fundamental_strength": "성장·마진·재무 안정성",
    "key_monitors": [
      "매주 모니터할 지표·일정"
    ],
    "position_sizing_view": "Core/Satellite/Trade 중 어느 성격 + 근거"
  },
  "value_chain": {
    "upstream": [
      "NVDA",
      "TSM"
    ],
    "midstream": [
      "005930",
      "000660"
    ],
    "downstream": [
      "MU"
    ]
  },
  "policy_tracker": [
    {
      "date": "2026-06-11",
      "title": "삼성전자, 외부 생성형 AI 전면 도입",
      "region": "KR",
      "stance": "supportive"
    }
  ],
  "disclaimer": "본 분석은 AI 생성 정보이며 투자 권유가 아닙니다.",
  "generatedAt": "2026-06-11T16:51:42.964Z",
  "_model": "llama-3.1-8b-instant"
}