{
  "updatedAt": "2026-07-05T17:04:15.853Z",
  "related": [
    {
      "slug": "젠슨황",
      "name": {
        "ko": "젠슨 황",
        "en": "Jensen Huang"
      },
      "icon": "🕴️",
      "tier": "hot",
      "overlap": 4
    },
    {
      "slug": "삼성전자",
      "name": {
        "ko": "삼성전자",
        "en": "Samsung Electronics"
      },
      "icon": "📱",
      "tier": "hot",
      "overlap": 4
    },
    {
      "slug": "AI인프라",
      "name": {
        "ko": "AI 인프라·데이터센터",
        "en": "AI Infrastructure"
      },
      "icon": "🏗️",
      "tier": "hot",
      "overlap": 4
    },
    {
      "slug": "엔비디아",
      "name": {
        "ko": "엔비디아",
        "en": "NVIDIA"
      },
      "icon": "🟩",
      "tier": "hot",
      "overlap": 3
    }
  ],
  "summary": "반도체 공장 증설 경쟁이 가열되고, 메모리 쇼크가 스마트폰 가격을 올려대고 있습니다. HBM·고대역폭메모리 테마는 반도체 산업의 성장과 수요 증가에 의해 주도되고 있습니다.",
  "sentiment": "bullish",
  "key_drivers": [
    "반도체 공장 증설 경쟁",
    "메모리 쇼크",
    "HBM·고대역폭메모리 수요 증가"
  ],
  "watch_points": [
    "반도체 공장 증설 경쟁의 심화",
    "메모리 쇼크의 지속",
    "HBM·고대역폭메모리 수요의 증가"
  ],
  "risks": [
    "반도체 공장 증설 경쟁의 심화",
    "메모리 쇼크의 지속",
    "HBM·고대역폭메모리 수요의 감소"
  ],
  "events": [
    {
      "date": "2026-07-05",
      "title": "마이크론, 히로시마에 14조 투자",
      "impact": "positive"
    }
  ],
  "key_players": [
    "삼성전자",
    "SK하이닉스",
    "마이크론",
    "엔비디아"
  ],
  "outlook": {
    "short_term": {
      "thesis": "반도체 공장 증설 경쟁과 메모리 쇼크가 지속되며, HBM·고대역폭메모리 수요가 증가할 것으로 예상됩니다. 반도체 공장 증설 경쟁의 심화와 메모리 쇼크의 지속은 반도체 산업의 성장과 수요 증가에 의해 주도될 것입니다.",
      "upside": "HBM·고대역폭메모리 수요가 증가할 경우, 반도체 공장 증설 경쟁의 심화와 메모리 쇼크의 지속은 반도체 산업의 성장과 수요 증가에 의해 주도될 것입니다.",
      "downside": "반도체 공장 증설 경쟁의 심화와 메모리 쇼크의 지속은 반도체 산업의 성장과 수요 증가에 의해 주도될 것입니다."
    },
    "mid_term": {
      "thesis": "반도체 공장 증설 경쟁과 메모리 쇼크가 지속되며, HBM·고대역폭메모리 수요가 증가할 것으로 예상됩니다. 반도체 공장 증설 경쟁의 심화와 메모리 쇼크의 지속은 반도체 산업의 성장과 수요 증가에 의해 주도될 것입니다.",
      "upside": "HBM·고대역폭메모리 수요가 증가할 경우, 반도체 공장 증설 경쟁의 심화와 메모리 쇼크의 지속은 반도체 산업의 성장과 수요 증가에 의해 주도될 것입니다.",
      "downside": "반도체 공장 증설 경쟁의 심화와 메모리 쇼크의 지속은 반도체 산업의 성장과 수요 증가에 의해 주도될 것입니다."
    },
    "long_term": {
      "thesis": "반도체 공장 증설 경쟁과 메모리 쇼크가 지속되며, HBM·고대역폭메모리 수요가 증가할 것으로 예상됩니다. 반도체 공장 증설 경쟁의 심화와 메모리 쇼크의 지속은 반도체 산업의 성장과 수요 증가에 의해 주도될 것입니다.",
      "upside": "HBM·고대역폭메모리 수요가 증가할 경우, 반도체 공장 증설 경쟁의 심화와 메모리 쇼크의 지속은 반도체 산업의 성장과 수요 증가에 의해 주도될 것입니다.",
      "downside": "반도체 공장 증설 경쟁의 심화와 메모리 쇼크의 지속은 반도체 산업의 성장과 수요 증가에 의해 주도될 것입니다."
    }
  },
  "capital_flow": {
    "summary": "반도체 공장 증설 경쟁과 메모리 쇼크가 지속되며, HBM·고대역폭메모리 수요가 증가할 것으로 예상됩니다.",
    "signals": [
      "미래에셋 스페이스X 2차 청약 완판"
    ]
  },
  "scenarios": [
    {
      "case": "기본(Base)",
      "probability": 60,
      "thesis": "반도체 공장 증설 경쟁과 메모리 쇼크가 지속되며, HBM·고대역폭메모리 수요가 증가할 것으로 예상됩니다.",
      "trigger": "반도체 공장 증설 경쟁의 심화",
      "watch_period": "1~2주",
      "data_quality": "full"
    },
    {
      "case": "강세(Bull)",
      "probability": 20,
      "thesis": "HBM·고대역폭메모리 수요가 증가할 경우, 반도체 공장 증설 경쟁의 심화와 메모리 쇼크의 지속은 반도체 산업의 성장과 수요 증가에 의해 주도될 것입니다.",
      "trigger": "HBM·고대역폭메모리 수요의 증가",
      "watch_period": "기간",
      "data_quality": "full"
    },
    {
      "case": "약세(Bear)",
      "probability": 20,
      "thesis": "반도체 공장 증설 경쟁의 심화와 메모리 쇼크의 지속은 반도체 산업의 성장과 수요 증가에 의해 주도될 것입니다.",
      "trigger": "반도체 공장 증설 경쟁의 심화",
      "watch_period": "기간",
      "data_quality": "full"
    }
  ],
  "pb_perspective": {
    "valuation_assessment": "HBM·고대역폭메모리 수요가 증가할 경우, 반도체 공장 증설 경쟁의 심화와 메모리 쇼크의 지속은 반도체 산업의 성장과 수요 증가에 의해 주도될 것입니다.",
    "momentum_signals": "반도체 공장 증설 경쟁의 심화와 메모리 쇼크의 지속은 반도체 산업의 성장과 수요 증가에 의해 주도될 것입니다.",
    "fundamental_strength": "반도체 공장 증설 경쟁의 심화와 메모리 쇼크의 지속은 반도체 산업의 성장과 수요 증가에 의해 주도될 것입니다.",
    "key_monitors": [
      "HBM ASP",
      "인증 동향",
      "DRAM/NAND 계약가",
      "삼성/SK DS 부문 OPM",
      "빅테크 데이터센터 CapEx"
    ],
    "position_sizing_view": "Core/Satellite/Trade"
  },
  "value_chain": {
    "upstream": [
      "042700"
    ],
    "midstream": [
      "000660",
      "005930",
      "MU"
    ],
    "downstream": [
      "NVDA"
    ]
  },
  "policy_tracker": [
    {
      "date": "2026-07-05",
      "title": "한은, 삼전닉스 레버리지에 경고",
      "region": "KR",
      "stance": "restrictive"
    },
    {
      "date": null,
      "title": "반도체 특별법",
      "region": "KR",
      "stance": "neutral"
    },
    {
      "date": null,
      "title": "CHIPS Act",
      "region": "US",
      "stance": "neutral"
    },
    {
      "date": null,
      "title": "EU Chips Act",
      "region": "US",
      "stance": "neutral"
    }
  ],
  "sector_kpis": [
    {
      "name": "HBM ASP·인증 동향",
      "value": "[확인 필요]",
      "source": "[확인 필요]",
      "trend": "unknown"
    },
    {
      "name": "DRAM/NAND 계약가",
      "value": "[확인 필요]",
      "source": "[확인 필요]",
      "trend": "unknown"
    },
    {
      "name": "삼성/SK DS 부문 OPM",
      "value": "[확인 필요]",
      "source": "[확인 필요]",
      "trend": "unknown"
    },
    {
      "name": "빅테크 데이터센터 CapEx",
      "value": "[확인 필요]",
      "source": "[확인 필요]",
      "trend": "unknown"
    },
    {
      "name": "재고 일수",
      "value": "[확인 필요]",
      "source": "[확인 필요]",
      "trend": "unknown"
    }
  ],
  "disclaimer": "본 분석은 AI 생성 정보이며 투자 권유가 아닙니다.",
  "generatedAt": "2026-07-05T17:03:41.091Z",
  "_model": "groq:llama-3.1-8b-instant"
}