{
  "updatedAt": "2026-06-09T04:44:03.159Z",
  "data": {
    "005930": {
      "name": "삼성전자",
      "px": 317000,
      "dayChange": 0,
      "currency": "KRW",
      "state": "CLOSED",
      "market": "KR"
    },
    "NVDA": {
      "name": "엔비디아",
      "px": 208.64,
      "dayChange": 0,
      "currency": "USD",
      "state": "CLOSED",
      "market": "US"
    },
    "TSM": {
      "name": "TSMC",
      "px": 426.8,
      "dayChange": 0,
      "currency": "USD",
      "state": "CLOSED",
      "market": "US"
    },
    "000660": {
      "name": "SK하이닉스",
      "px": 2139000,
      "dayChange": 0,
      "currency": "KRW",
      "state": "CLOSED",
      "market": "KR"
    },
    "MU": {
      "name": "마이크론",
      "px": 949.28,
      "dayChange": 0,
      "currency": "USD",
      "state": "CLOSED",
      "market": "US"
    }
  }
}